fedops/__init__.py
fedops/client/__init__.py
fedops/client/app.py
fedops/client/client_api.py
fedops/client/client_fl.py
fedops/client/client_utils.py
fedops/client/client_wandb.py
fedops/client/test.py
fedops/server/__init__.py
fedops/server/app.py
fedops/server/mobile_app.py
fedops/server/mobile_strategy.py
fedops/server/server_api.py
fedops/server/server_utils.py
fedops/simulation/__init__.py
fedops/simulation/app.py
fedops/simulation/fl_strategy/__init__.py
fedops/simulation/fl_strategy/aggregation.py
fedops/simulation/fl_strategy/client.py
fedops/simulation/fl_strategy/selection.py
fedops/simulation/fl_strategy/server.py
fedops/utils/__init__.py
fedops/utils/version.py
fedops_test-0.3.0.dist-info/METADATA
fedops_test-0.3.0.dist-info/WHEEL
fedops_test-0.3.0.dist-info/top_level.txt
fedops_test-0.3.0.dist-info/RECORD
