Metadata-Version: 2.1
Name: fedops-test
Version: 0.3.0
Summary: FL Lifecycle Operations Management Platform
Home-page: https://github.com/gachon-CCLab/FedOps.git
Author: Semo Yang
Author-email: tpah20@gmail.com
Classifier: Development Status :: 5 - Production/Stable
Classifier: License :: OSI Approved :: MIT License
Classifier: Programming Language :: Python :: 3
Classifier: Programming Language :: Python :: 3.7
Classifier: Programming Language :: Python :: 3.8
Classifier: Programming Language :: Python :: 3.9
Classifier: Programming Language :: Python :: 3.10
Classifier: Programming Language :: Python :: 3.11
Requires-Dist: flwr (>=1.0.0)
Requires-Dist: flwr[simulation]
Requires-Dist: fastapi (>=0.70.1)
Requires-Dist: uvicorn[standard] (>=0.16.0)
Requires-Dist: requests (>=2.26.0)
Requires-Dist: pydantic (>=1.10.7)
Requires-Dist: numpy (>=1.23.5)
Requires-Dist: wandb (>=0.15.0)
Requires-Dist: pandas (>=1.5.3)
Requires-Dist: pyyaml (>=5.0)
Requires-Dist: boto3 (>=1.24.0)
Requires-Dist: numba
